reno/__init__.py
reno/components.py
reno/diagrams.py
reno/explorer.py
reno/interactive_latex.py
reno/model.py
reno/ops.py
reno/parser.py
reno/pymc.py
reno/tab_exporter.py
reno/utils.py
reno/viz.py
reno/res/interactive_latex.vue
reno_sd-0.8.1.dist-info/licenses/LICENSE
reno_sd-0.8.1.dist-info/METADATA
reno_sd-0.8.1.dist-info/WHEEL
reno_sd-0.8.1.dist-info/top_level.txt
reno_sd-0.8.1.dist-info/RECORD
