Metadata-Version: 2.4
Name: reno-sd
Version: 0.8.1
Summary: System dynamics modeling with bayesian inference
Author-email: "Nathan Martindale, Jordan Stomps, Birdy Phathanapirom" <martindalena@ornl.gov>
License-Expression: BSD-3-Clause
Project-URL: Repository, https://github.com/ORNL/reno
Project-URL: Changelog, https://github.com/ORNL/reno/blob/main/CHANGELOG.md
Project-URL: Issues, https://github.com/ORNL/reno/issues
Project-URL: Documentation, https://ornl.github.io/reno/stable
Keywords: system dynamics,sdm,simulation,reno,pymc,bayesian
Classifier: Development Status :: 4 - Beta
Classifier: Intended Audience :: Science/Research
Classifier: Operating System :: OS Independent
Classifier: Topic :: Scientific/Engineering
Classifier: Programming Language :: Python :: 3
Classifier: Programming Language :: Python :: 3.11
Classifier: Programming Language :: Python :: 3.12
Classifier: Programming Language :: Python :: 3.13
Requires-Python: <3.14,>=3.11
License-File: LICENSE
Requires-Dist: numpy
Requires-Dist: pandas
Requires-Dist: xarray
Requires-Dist: panel
Requires-Dist: pymc
Requires-Dist: matplotlib
Requires-Dist: selenium
Requires-Dist: ipyvuetify
Requires-Dist: graphviz
Dynamic: license-file
